<?xml version="1.0" encoding="utf-8"?>
<pack>
  <tiles>
    <tile id="KR/LC">
      <cloister />
      <city castle-base="true">N</city>
      <farm city="N">EL ER SL SR WL WR</farm>
    </tile>
    <tile id="KR/RC">
      <road>W</road>
      <city castle-base="true">N</city>
      <farm city="N">WR</farm>
      <farm city="N">EL ER SL SR WL</farm>
      <wagon-move>
        <neighbouring>N W</neighbouring>
      </wagon-move>
    </tile>
    <tile id="KR/RCG">
      <garden/>
      <road>W</road>
      <city castle-base="true">N</city>
      <farm city="N">WR</farm>
      <farm city="N">EL ER SL SR WL</farm>
      <wagon-move>
        <neighbouring>N W</neighbouring>
      </wagon-move>
    </tile>
    <tile id="KR/CRrR">
      <road>W</road>
      <road>S E</road>
      <city castle-base="true">N</city>
      <farm city="N">WR</farm>
      <farm city="N">EL SR WL</farm>
      <farm>SL ER</farm>
      <wagon-move>
        <neighbouring>N W</neighbouring>
      </wagon-move>
    </tile>
    <tile id="KR/CcRR!">
      <road>S</road>
      <road>E</road>
      <city>N W</city>
      <farm city="N">SR</farm>
      <farm city="N">SL</farm>
      <farm city="N">ER</farm>
      <farm city="N">EL</farm>
      <wagon-move>
        <neighbouring>N E</neighbouring>
        <neighbouring>N S</neighbouring>
      </wagon-move>
    </tile>
    <tile id="KR/CCcc">
      <city>W E</city>
      <city>N S</city>
      <farm city="N W">INNER_FARM</farm>
      <farm city="N W">INNER_FARM_B</farm>
    </tile>
  </tiles>
  <sets>
    <tile-set id="king-and-robber:1">
      <ref count="1" tile="KR/LC" />
      <ref count="1" tile="KR/RC" />
      <ref count="1" tile="KR/CRrR" />
      <ref count="1" tile="KR/CcRR!" />
      <ref count="1" tile="KR/CCcc" />
    </tile-set>
    <tile-set id="king-and-robber:2">
      <ref count="1" tile="KR/LC" />
      <ref count="1" tile="KR/RCG" />
      <ref count="1" tile="KR/CRrR" />
      <ref count="1" tile="KR/CcRR!" />
      <ref count="1" tile="KR/CCcc" />
    </tile-set>
  </sets>
</pack>
